pyfinance/__init__.py
pyfinance/datasets.py
pyfinance/general.py
pyfinance/ols.py
pyfinance/options.py
pyfinance/returns.py
pyfinance/utils.py
pyfinance-1.3.0.dist-info/LICENSE
pyfinance-1.3.0.dist-info/METADATA
pyfinance-1.3.0.dist-info/WHEEL
pyfinance-1.3.0.dist-info/top_level.txt
pyfinance-1.3.0.dist-info/RECORD
