Metadata-Version: 2.1
Name: pyfinance
Version: 1.3.0
Summary: Python package designed for security returns analysis.
Home-page: https://github.com/bsolomon1124/pyfinance
Author: Brad Solomon
Author-email: bsolomon@protonmail.com
License: MIT
Keywords: finance,investment,analysis,regression,options,securities,CAPM,machine learning,risk
Platform: UNKNOWN
Classifier: Development Status :: 4 - Beta
Classifier: Intended Audience :: Developers
Classifier: Intended Audience :: Financial and Insurance Industry
Classifier: Intended Audience :: Science/Research
Classifier: Programming Language :: Python :: 3
Classifier: Programming Language :: Python :: 3.5
Classifier: Programming Language :: Python :: 3.6
Classifier: Programming Language :: Python :: 3.7
Classifier: Programming Language :: Python :: 3.8
Classifier: Programming Language :: Python :: 3.9
Classifier: Topic :: Office/Business :: Financial
Classifier: Topic :: Office/Business :: Financial :: Investment
Classifier: Topic :: Scientific/Engineering :: Information Analysis
Requires-Python: >=3
